wayland_mcp/__init__.py
wayland_mcp/add_rulers.py
wayland_mcp/app.py
wayland_mcp/chain_processor.py
wayland_mcp/keyboard_utils.py
wayland_mcp/keymap.py
wayland_mcp/mouse_utils.py
wayland_mcp/requirements.txt
wayland_mcp/screen_utils.py
wayland_mcp/server_mcp.py
wayland_mcp-0.4.0.dist-info/METADATA
wayland_mcp-0.4.0.dist-info/WHEEL
wayland_mcp-0.4.0.dist-info/entry_points.txt
wayland_mcp-0.4.0.dist-info/RECORD
