Metadata-Version: 2.4
Name: wayland-mcp
Version: 0.4.0
Summary: Wayland MCP server (Python, uvx-compatible)
Project-URL: repository, https://github.com/someaka/wayland-mcp
Author: someaka
Requires-Python: >=3.8
Requires-Dist: fastmcp
Requires-Dist: pillow
Requires-Dist: requests
